elevenlabs_mcp/__init__.py
elevenlabs_mcp/__main__.py
elevenlabs_mcp/convai.py
elevenlabs_mcp/model.py
elevenlabs_mcp/server.py
elevenlabs_mcp/utils.py
elevenlabs_mcp-0.9.1.dist-info/licenses/LICENSE
elevenlabs_mcp-0.9.1.dist-info/METADATA
elevenlabs_mcp-0.9.1.dist-info/WHEEL
elevenlabs_mcp-0.9.1.dist-info/entry_points.txt
elevenlabs_mcp-0.9.1.dist-info/top_level.txt
elevenlabs_mcp-0.9.1.dist-info/RECORD
